Metadata-Version: 2.1
Name: pytest-tstcls
Version: 2020.1.1
Summary: Test Class Base
Home-page: https://github.com/singular-labs/tstcls
Author: Singular Labs, Inc
Author-email: devs@singular.net
License: MIT License
Keywords: pytest,test,class,base
Platform: UNKNOWN
Classifier: Development Status :: 5 - Production/Stable
Classifier: Intended Audience :: Developers
Classifier: Topic :: Software Development :: Build Tools
Classifier: License :: OSI Approved :: MIT License
Classifier: Programming Language :: Python :: 2.7
Classifier: Programming Language :: Python :: 3.4
Classifier: Programming Language :: Python :: 3.5
Classifier: Programming Language :: Python :: 3.6
Provides: tstcls
Requires-Python: >=2.6, !=3.0.*, !=3.1.*, !=3.2.*, !=3.3.*
